tkr/__init__.py
tkr/__main__.py
tkr/cli.py
tkr/abc/__init__.py
tkr/abc/_tool.py
tkr/core/__init__.py
tkr/core/changelog.py
tkr/core/coreattrs.json
tkr/ext/__init__.py
tkr/ext/driver/__init__.py
tkr/resource/__init__.py
tkr-0.2.1.post1.dist-info/LICENSE
tkr-0.2.1.post1.dist-info/METADATA
tkr-0.2.1.post1.dist-info/WHEEL
tkr-0.2.1.post1.dist-info/entry_points.txt
tkr-0.2.1.post1.dist-info/top_level.txt
tkr-0.2.1.post1.dist-info/RECORD
