Metadata-Version: 2.1
Name: tkr
Version: 0.2.1.post1
Summary: Python Toolkit
Home-page: https://github.com/toolkitr/tkr
Author: tlkr.
Author-email: "tlkr." <toolkitr.email@gmail.com>
License: The MIT License (MIT)
Project-URL: Homepage, https://github.com/toolkitr/tkr
Project-URL: Discussions, https://github.com/toolkitr/tkr/discussions
Project-URL: PullRequest, https://github.com/toolkitr/tkr/pulls
Project-URL: Issues, https://github.com/toolkitr/tkr/issues
Keywords: tkr,toolkitr
Classifier: License :: OSI Approved :: MIT License
Classifier: Development Status :: 1 - Planning
Classifier: Intended Audience :: Developers
Classifier: License :: OSI Approved :: MIT License
Classifier: Programming Language :: Python
Classifier: Programming Language :: Python :: 3.10
Classifier: Programming Language :: Python :: 3.11
Classifier: Topic :: Internet
Classifier: Topic :: Software Development :: Libraries
Classifier: Topic :: Software Development :: Libraries :: Python Modules
Classifier: Topic :: Utilities
Classifier: Typing :: Typed
Requires-Python: >=3.10.0,<3.12
License-File: LICENSE
Requires-Dist: asyncio >=3.4.3
Requires-Dist: async-timeout >=3.0.1
